analytics/__init__.py
analytics/investment_statistics.py
analytics/metrics.py
analytics/statistics.py
finance/__init__.py
finance/growth.py
finance/main.py
finance/returns.py
finance/risk.py
investments/__init__.py
investments/calculator.py
introtopython_okechio_finance_tools-0.2.0.dist-info/METADATA
introtopython_okechio_finance_tools-0.2.0.dist-info/WHEEL
introtopython_okechio_finance_tools-0.2.0.dist-info/top_level.txt
introtopython_okechio_finance_tools-0.2.0.dist-info/RECORD
